.DS_Store
microservices_connector/Interservices.py
microservices_connector/__init__.py
microservices_connector/minisocket.py
microservices_connector/socket.py
microservices_connector/spawn.py
microservices_connector/url_parser/__init__.py
microservices_connector/url_parser/url_namespace.py
microservices_connector-0.3.7.dist-info/DESCRIPTION.rst
microservices_connector-0.3.7.dist-info/METADATA
microservices_connector-0.3.7.dist-info/RECORD
microservices_connector-0.3.7.dist-info/WHEEL
microservices_connector-0.3.7.dist-info/metadata.json
microservices_connector-0.3.7.dist-info/top_level.txt
